slack_discovery_sdk/__init__.py
slack_discovery_sdk/base_client.py
slack_discovery_sdk/client.py
slack_discovery_sdk/errors.py
slack_discovery_sdk/internal_utils.py
slack_discovery_sdk/oauth.py
slack_discovery_sdk/proxy_support.py
slack_discovery_sdk/rate_limit_support.py
slack_discovery_sdk/response.py
slack_discovery_sdk/version.py
slack_discovery_sdk/examples/DLP_call_pattern.py
slack_discovery_sdk/examples/__init__.py
slack_discovery_sdk/examples/audit_logs_pattern.py
slack_discovery_sdk/examples/get_enterprise_info.py
slack_discovery_sdk/examples/user_based_eDiscovery_pattern.py
slack_discovery_sdk/examples/user_based_eDiscovery_with_edits.py
slack_discovery_sdk/examples/utils.py
slack_discovery_sdk-1.0.2.dist-info/LICENSE.md
slack_discovery_sdk-1.0.2.dist-info/METADATA
slack_discovery_sdk-1.0.2.dist-info/WHEEL
slack_discovery_sdk-1.0.2.dist-info/top_level.txt
slack_discovery_sdk-1.0.2.dist-info/RECORD
