Metadata-Version: 2.1
Name: slack-discovery-sdk
Version: 1.0.2
Summary: The Slack Discovery API SDK for Python
Author: Slack Technologies, LLC
Classifier: Programming Language :: Python :: 3.6
Classifier: Programming Language :: Python :: 3.7
Classifier: Programming Language :: Python :: 3.8
Classifier: Programming Language :: Python :: 3.9
Classifier: Programming Language :: Python :: 3.10
Classifier: Programming Language :: Python :: 3.11
Classifier: Programming Language :: Python :: Implementation :: CPython
Classifier: Operating System :: OS Independent
Requires-Python: >=3.6
License-File: LICENSE.md
Provides-Extra: testing
Requires-Dist: slack-sdk (<4,>=3.21.3) ; extra == 'testing'
Requires-Dist: pytest (<7,>=6) ; extra == 'testing'
Requires-Dist: pytest-cov (<4,>=3) ; extra == 'testing'
Requires-Dist: black (==22.8.0) ; extra == 'testing'
